kiutra_pypi_test/__init__.py
kiutra_pypi_test/hello_world.py
kiutra_pypi_test-0.0.0a1.dist-info/METADATA
kiutra_pypi_test-0.0.0a1.dist-info/WHEEL
kiutra_pypi_test-0.0.0a1.dist-info/top_level.txt
kiutra_pypi_test-0.0.0a1.dist-info/RECORD
