Metadata-Version: 2.1
Name: kiutra_pypi_test
Version: 0.0.0a1
Summary: A python package to check how pypi packages work.
Home-page: 
Download-URL: 
Author: kiutra GmbH
Author-email: info@kiutra.com
Maintainer: 
Maintainer-email: Rafael Hefele <rafael.hefele@kiutra.com>
Requires-Python: >=3.7
